my_own_package/__init__.py
Luci_first_package-0.3.0.dist-info/METADATA
Luci_first_package-0.3.0.dist-info/WHEEL
Luci_first_package-0.3.0.dist-info/top_level.txt
Luci_first_package-0.3.0.dist-info/RECORD
