Metadata-Version: 2.1
Name: Luci-first-package
Version: 0.3.0
Summary: This is my first package,get pwnd noobs.
Home-page: UNKNOWN
Author: Lucian
Author-email: stardust0010@yahoo.com
License: UNKNOWN
Platform: UNKNOWN
